autosort_neuron/__init__.py
autosort_neuron/config.py
autosort_neuron/detection.py
autosort_neuron/model.py
autosort_neuron/run.py
autosort_neuron/sma.py
autosort_neuron/sorting.py
autosort_neuron/utils.py
autosort_neuron/waveform_loader.py
autosort_neuron/intanutil/__init__.py
autosort_neuron/intanutil/data_to_result.py
autosort_neuron/intanutil/get_bytes_per_data_block.py
autosort_neuron/intanutil/notch_filter.py
autosort_neuron/intanutil/qstring.py
autosort_neuron/intanutil/read_header.py
autosort_neuron/intanutil/read_one_data_block.py
autosort_neuron-0.0.1.3.dist-info/LICENSE
autosort_neuron-0.0.1.3.dist-info/METADATA
autosort_neuron-0.0.1.3.dist-info/WHEEL
autosort_neuron-0.0.1.3.dist-info/top_level.txt
autosort_neuron-0.0.1.3.dist-info/RECORD
