Metadata-Version: 2.1
Name: autosort-neuron
Version: 0.0.1.3
License-File: LICENSE
Requires-Dist: spikeinterface[full,widgets]
Requires-Dist: torch
Requires-Dist: pandas
Requires-Dist: scikit-learn
Requires-Dist: matplotlib
Requires-Dist: scipy
Requires-Dist: networkx
